p9hsci/__init__.py
p9hsci-0.1.2.dist-info/METADATA
p9hsci-0.1.2.dist-info/WHEEL
p9hsci-0.1.2.dist-info/RECORD
