Metadata-Version: 2.1
Name: p9hsci
Version: 0.1.2
Summary: HSCI theme for plotnine
License: MIT
Author: Eetu Mäkelä
Author-email: eetu.makela@iki.fi
Requires-Python: >=3.9
Classifier: License :: OSI Approved :: MIT License
Classifier: Programming Language :: Python :: 3
Classifier: Programming Language :: Python :: 3.9
Classifier: Programming Language :: Python :: 3.10
Classifier: Programming Language :: Python :: 3.11
Classifier: Programming Language :: Python :: 3.12
Requires-Dist: plotnine (>=0.13.0)
